commentator/__init__.py
commentator/__main__.py
commentator/collect_types.py
commentator/commentator.py
commentator/strip_comments.py
commentator/strip_imports.py
commentator/strip_types.py
python_commentator-0.3.0.dist-info/LICENSE
python_commentator-0.3.0.dist-info/METADATA
python_commentator-0.3.0.dist-info/WHEEL
python_commentator-0.3.0.dist-info/entry_points.txt
python_commentator-0.3.0.dist-info/top_level.txt
python_commentator-0.3.0.dist-info/RECORD
