Metadata-Version: 2.1
Name: python-commentator
Version: 0.3.0
Summary: An automatic commenter and type inference tool for Python code.
Author-email: Emery Berger <emery.berger@gmail.com>
Project-URL: Homepage, https://github.com/plasma-umass/commentator
Project-URL: Bug Tracker, https://github.com/plasma-umass/commentator
Classifier: Programming Language :: Python :: 3
Classifier: License :: OSI Approved :: MIT License
Classifier: Operating System :: OS Independent
Requires-Python: >=3.7
License-File: LICENSE
Requires-Dist: boto3 >=1.34.35
Requires-Dist: openai >=1.3.6
Requires-Dist: rich >=12.4.4
Requires-Dist: ast-comments >=1.0.0
Requires-Dist: click >=8.1.3
Requires-Dist: litellm >=1.22.3
Requires-Dist: mypy ==1.8.0
Requires-Dist: mypy-extensions ==1.0.0
Requires-Dist: async-generator ==1.10
